{"main":{"language":"en","lastHostname":"192.168.10.14","darkTheme":false,"useBinaryPrefix":true,"disableAutoComplete":false,"settingsStorageLocal":false,"settingsSaveDelay":2000,"cacheStorageLocal":true,"cacheSaveDelay":4000,"notifications":{"errorsPersistent":true,"timeout":5000},"webcam":{"url":"","updateInterval":5000,"liveUrl":"","useFix":false,"embedded":false,"rotation":0,"flip":"none"},"enabledPlugins":["Height Map"],"plugins":{}},"machine":{"ajaxRetries":2,"updateInterval":250,"extendedUpdateEvery":20,"fileTransferRetryThreshold":358400,"crcUploads":true,"pingInterval":2000,"updateDelay":0,"babystepAmount":0.05,"codes":["M0","M1","M115","M201 X500.00 Y500.00 Z20.00 E250.00:250","M203 X6000.00 Y6000.00 Z180.00 E1200.00:1200.00","M350 X16 Y16 I1","M350 X16 Y16 Z16 E16:16 I1","M564 S0 H0","M566 X900.00 Y900.00 Z60.00 E120.00:120.00","M569 P0.0 S1","M569 P0.1 S0","M569 P0.2 S0","M584 X0 Y1 Z2:3 E4:5","M584 X0 Y1 Z2:3 E4:5  4","M584 X0.0 Y0.1 Z0.2","M584 X0.0 Y0.1:0.2 Z1.0:1.1:1.2","M587","M84","M906","M906 X800 Y800 Z800 E800:800 I30","M906 X800 Y800 Z800 U800 V800 E800:800 I30","M92","M92 X80.00 Y80.00 Z400.00","M92 X80.00 Y80.00 Z400.00 E420.00:420.00","M997","echo network.interfaces[0].type","m906"],"displayedExtraTemperatures":[],"displayedExtruders":[0,1],"displayedFans":[-1,0,1,2],"moveSteps":{"X":[100,50,10,1,0.1],"Y":[100,50,10,1,0.1],"Z":[50,25,5,0.5,0.05],"default":[100,50,10,1,0.1]},"moveFeedrate":6000,"extruderAmounts":[100,50,20,10,5,1],"extruderFeedrates":[60,30,15,5,1],"temperatures":{"tool":{"active":[250,235,220,205,195,160,120,100,0],"standby":[210,180,160,140,0]},"bed":{"active":[110,100,90,70,65,60,0],"standby":[40,30,0]},"chamber":[90,80,70,60,50,40,0]},"spindleRPM":[10000,75000,5000,2500,1000,0],"enabledPlugins":[],"plugins":{}}}